[
  {
    "id": 1,
    "src": null,
    "name": "Elavon Commerce SDK",
    "description": [
      {
        "sidebarlist": [
          {
            "id": 1,
            "name": "Elavon Commerce SDK Overview",
            "sublist": [],
            "description": {
              "id": 0,
              "body": "<h1> Demo </h1> <h2>Main Heading</h2>"
            }
          },
          {
            "id": 2,
            "name": "Getting Started",
            "sublist": [],
            "description": {
              "body": "Demo2"
            }
          },
          {
            "id": 3,
            "name": "Integration Methods",
            "sublist": [
              {
                "id": 1,
                "name": "Commerce Web Services",
                "description": ""
              },
              {
                "id": 2,
                "name": "Java (Windows)",
                "description": ""
              },
              {
                "id": 3,
                "name": "Java (Android)",
                "description": ""
              },
              {
                "id": 4,
                "name": "Objective-C (iOS)",
                "description": ""
              },
              {
                "id": 5,
                "name": "C#",
                "description": ""
              }
            ],
            "description": {
              "body": "Demo 3"
            }
          }
        ]
      }
    ]
  },
  {
    "id": 2,
    "src": null,
    "name": "CashWave",
    "description": [
      {
        "sidebarlist": [
          {
            "id": 1,
            "name": " CashWave Overview",
            "sublist": [],
            "description": {
              "body": "",
              "heading": "",
              "content": ""
            }
          },
          {
            "id": 2,
            "name": "About CashWave",
            "sublist": [],
            "description": {
              "body": "",
              "heading": "",
              "content": ""
            }
          },
          {
            "id": 3,
            "name": "CashWave Integration",
            "sublist": [
              {
                "id": 1,
                "name": "ATM Services",
                "description": ""
              },
              {
                "id": 2,
                "name": "Java (Windows)",
                "description": ""
              },
              {
                "id": 3,
                "name": "Java (Android)",
                "description": ""
              },
              {
                "id": 4,
                "name": "Objective-C (iOS)",
                "description": ""
              },
              {
                "id": 5,
                "name": "C#",
                "description": ""
              }
            ],
            "description": {
              "body": "",
              "heading": "",
              "content": ""
            }
          }
        ]
      }
    ]
  },
  {
    "id": 3,
    "src": null,
    "name": "OrangeSoft",
    "description": [
      {
        "sidebarlist": [
          {
            "id": 1,
            "name": "About OrangeSoft",
            "sublist": [],
            "description": {
              "body": "",
              "heading": "",
              "content": ""
            }
          },
          {
            "id": 2,
            "name": "Pricing",
            "sublist": [],
            "description": {
              "body": "",
              "heading": "",
              "content": ""
            }
          },
          {
            "id": 3,
            "name": "Mobile Apps Integration",
            "sublist": [
              {
                "id": 1,
                "name": "iOS",
                "description": ""
              },
              {
                "id": 2,
                "name": "Android",
                "description": ""
              },
              {
                "id": 3,
                "name": "Tablet",
                "description": ""
              }
            ],
            "description": {
              "body": "",
              "heading": "",
              "content": ""
            }
          }
        ]
      }
    ]
  }
]
